tag2ver.py
tag2ver-1.4.2.dist-info/LICENSE
tag2ver-1.4.2.dist-info/METADATA
tag2ver-1.4.2.dist-info/WHEEL
tag2ver-1.4.2.dist-info/top_level.txt
tag2ver-1.4.2.dist-info/RECORD
