Metadata-Version: 2.2
Name: tag2ver
Version: 1.4.2
Summary: Easy release management: file versioning, git commit, git tagging, and optionally git remote, and PyPI.
Home-page: https://github.com/hlovatt/tag2ver
Author: Howard C Lovatt.
Author-email: howard.lovatt@gmail.com
License: MIT License
Platform: any
Classifier: Intended Audience :: Developers
Classifier: Programming Language :: Python :: 3
Classifier: License :: OSI Approved :: MIT License
Classifier: Operating System :: OS Independent
Requires-Python: >=3.9
License-File: LICENSE
Dynamic: author
Dynamic: author-email
Dynamic: classifier
Dynamic: description
Dynamic: description-content-type
Dynamic: home-page
Dynamic: license
Dynamic: platform
Dynamic: requires-python
Dynamic: summary
